config/comp_bin_mgtd.yaml
config/comp_case2024-climate.yaml
config/comp_case2024-climate_matrix.yaml
config/comp_case2024-climate_matrix_multiprompt.yaml
config/comp_case2024-climate_matrix_multiprompt_custom_examples.yaml
config/comp_case2024-climate_matrix_multiprompt_messages.yaml
config/comp_case2024-climate_matrix_no_rerank.yaml
config/comp_case2024-climate_matrix_no_retrieval.yaml
config/comp_case2024-climate_matrix_with_custom_examples.yaml
config/example_ag_news.yaml
config/example_ag_news_alt_model.yaml
config/example_ag_news_cde.yaml
config/example_bin_mgtd.yaml
config/example_bin_mgtd_out_f.yaml
config/example_cnn_daily.yaml
config/example_cnn_daily_batch_size.yaml
config/example_dialogsum.yaml
config/example_imdb.yaml
config/example_stocks_tweets.yaml
config/single-shot-example-function-calling-messages-get-weather.yaml
config/single-shot-example-function-calling-messages-not-last.yaml
config/single-shot-example-function-calling-messages.yaml
config/single-shot-example-function-calling.yaml
config/single-shot-example-preprocessor.yaml
config/single-shot-example.yaml
ragthoven/__init__.py
ragthoven/constants.py
ragthoven/executors/__init__.py
ragthoven/executors/cde_embedder.py
ragthoven/executors/embedder.py
ragthoven/executors/output_writer.py
ragthoven/executors/preprocessor.py
ragthoven/executors/prompt_executor.py
ragthoven/executors/prompt_formatter.py
ragthoven/executors/reranker.py
ragthoven/models/__init__.py
ragthoven/models/base.py
ragthoven/models/iter_matrix.py
ragthoven/standalone.py
ragthoven/test/__init__.py
ragthoven/test/test_data/SubTask-A-test.csv
ragthoven/test/test_data/SubTask-A-train.csv
ragthoven/test/test_intensive.py
ragthoven/test/test_preprocessor.py
ragthoven/test/test_simple.py
ragthoven/tools/README.md
ragthoven/tools/__init__.py
ragthoven/tools/example_fun_calling.py
ragthoven/tools/example_tool.py
ragthoven/utils/__init__.py
ragthoven/utils/config_loader.py
ragthoven/utils/dataset_loader.py
ragthoven-0.2.3.dist-info/LICENSE
ragthoven-0.2.3.dist-info/METADATA
ragthoven-0.2.3.dist-info/WHEEL
ragthoven-0.2.3.dist-info/entry_points.txt
ragthoven-0.2.3.dist-info/RECORD
