Metadata-Version: 2.1
Name: ragthoven
Version: 0.2.3
Summary: 
Author: Gregor Karetka
Author-email: karetka.gregor@gmail.com
Requires-Python: >=3.10,<4.0
Classifier: Programming Language :: Python :: 3
Classifier: Programming Language :: Python :: 3.10
Classifier: Programming Language :: Python :: 3.11
Classifier: Programming Language :: Python :: 3.12
Classifier: Programming Language :: Python :: 3.13
Requires-Dist: accelerate (>=0.34.2,<0.35.0)
Requires-Dist: chromadb (>=0.5.5,<0.6.0)
Requires-Dist: datasets (>=2.21.0,<3.0.0)
Requires-Dist: einops (>=0.8.0,<0.9.0)
Requires-Dist: flashrank (>=0.2.9,<0.3.0)
Requires-Dist: jinja2 (>=3.1.4,<4.0.0)
Requires-Dist: litellm (>=1.44.14,<2.0.0)
Requires-Dist: openai (>=1.42.0,<2.0.0)
Requires-Dist: protobuf (<3.20)
Requires-Dist: python-dotenv (>=0.19.2,<0.20.0)
Requires-Dist: pyyaml (>=6.0.2,<7.0.0)
Requires-Dist: sentence-transformers (>=3.1.1,<4.0.0)
Requires-Dist: tqdm (>=4.66.5,<5.0.0)
Requires-Dist: transformers (>=4.48,<5.0)
Requires-Dist: typer (>=0.12.5,<0.13.0)
